LICENSE
MANIFEST.in
README.md
VERSION
requirements.txt
setup.py
wera2netcdf/__init__.py
wera2netcdf/wera.py
wera2netcdf.egg-info/PKG-INFO
wera2netcdf.egg-info/SOURCES.txt
wera2netcdf.egg-info/dependency_links.txt
wera2netcdf.egg-info/requires.txt
wera2netcdf.egg-info/top_level.txt
wera2netcdf/tests/__init__.py
wera2netcdf/tests/test_convert.py