Metadata-Version: 1.1
Name: wera2netcdf
Version: 0.0.4
Summary: A utility to convert WERA total ASCII files into CF NetCDF files.
Home-page: https://github.com/axiom-data-science/wera2netcdf
Author: Kyle Wilcox
Author-email: kyle@axiomdatascience.com
License: MIT
Platform: UNKNOWN
Classifier: Development Status :: 3 - Alpha
Classifier: Intended Audience :: Developers
Classifier: Intended Audience :: Science/Research
Classifier: License :: OSI Approved :: MIT License
Classifier: Operating System :: POSIX :: Linux
Classifier: Programming Language :: Python
Classifier: Topic :: Scientific/Engineering
